ipproxy.py
ipproxy-0.1.1.dist-info/METADATA
ipproxy-0.1.1.dist-info/WHEEL
ipproxy-0.1.1.dist-info/top_level.txt
ipproxy-0.1.1.dist-info/RECORD
